icare/__init__.py
icare/base.py
icare/classification.py
icare/metrics.py
icare/ranker.py
icare/survival.py
icare/visualisation.py
icare-0.1.0.dist-info/LICENSE
icare-0.1.0.dist-info/METADATA
icare-0.1.0.dist-info/WHEEL
icare-0.1.0.dist-info/top_level.txt
icare-0.1.0.dist-info/RECORD
